binhoHostAdapter/__init__.py
binhoHostAdapter/binhoHostAdapter.py
binhoHostAdapter/binhoUtilities.py
binho_host_adapter-0.1.6.dist-info/LICENSE
binho_host_adapter-0.1.6.dist-info/METADATA
binho_host_adapter-0.1.6.dist-info/WHEEL
binho_host_adapter-0.1.6.dist-info/top_level.txt
binho_host_adapter-0.1.6.dist-info/RECORD
