Metadata-Version: 2.1
Name: binho-host-adapter
Version: 0.1.6
Summary: Python Libraries for Binho Multi-Protocol USB Host Adapters
Home-page: https://binho.io
Author: Binho LLC
Author-email: support@binho.io
License: UNKNOWN
Platform: UNKNOWN
Classifier: Programming Language :: Python :: 3
Classifier: License :: OSI Approved :: MIT License
Classifier: Operating System :: OS Independent
